pysteamsignin/__init__.py
pysteamsignin/steamsignin.py
steamsignin-1.1.3.dist-info/licenses/LICENSE
steamsignin-1.1.3.dist-info/METADATA
steamsignin-1.1.3.dist-info/WHEEL
steamsignin-1.1.3.dist-info/top_level.txt
steamsignin-1.1.3.dist-info/RECORD
