Metadata-Version: 2.4
Name: steamsignin
Version: 1.1.3
Summary: OpenID 2.0 sign in for Steam
Home-page: https://github.com/TeddiO/pySteamSignIn
Author: TeddiO
Author-email: 
Project-URL: Bug Tracker, https://github.com/TeddiO/pySteamSignIn/issues
Classifier: Programming Language :: Python :: 3
Classifier: License :: OSI Approved :: GNU General Public License v2 (GPLv2)
Classifier: Operating System :: OS Independent
Requires-Python: >=3.6
License-File: LICENSE
Dynamic: author
Dynamic: classifier
Dynamic: description
Dynamic: description-content-type
Dynamic: home-page
Dynamic: license-file
Dynamic: project-url
Dynamic: requires-python
Dynamic: summary
